dual_port_ram.v
//Dual Port RAM

module dual_port_RAM(CLK,CS,WR_RD_A,WR_RD_B,ADDR_A,ADDR_B,WDATA_A,WDATA_B,RDATA_A,RDATA_B);
  
  parameter N = 4;  //No. of Address Lines
  parameter D = 16; //Depth of Memory
  parameter W = 8;  //Width of Memory
  
  input CLK,CS,WR_RD_A,WR_RD_B;
  input [N-1:0] ADDR_A,ADDR_B;
  input [W-1:0] WDATA_A,WDATA_B;
  output reg [W-1:0] RDATA_A,RDATA_B;
  
  reg [W-1:0] mem [D-1:0];
  integer i;
  
  //Port A
  always@(posedge CLK)
    begin
      if(!CS)  //chip selected
        begin
          if(WR_RD_A)
            mem[ADDR_A] <= WDATA_A;
          else
            RDATA_A <= mem[ADDR_A];
        end
    end
  
  //Port B
  always@(posedge CLK)
    begin
      if(!CS)  //chip selected
        begin
          if(WR_RD_B)
            mem[ADDR_B] <= WDATA_B;
          else
            RDATA_B <= mem[ADDR_B];
        end
    end
  
  
  endmodule

dual_port_ram_tb.v
module tb;
  
  reg clk,cs,wr_rd_a,wr_rd_b;
  reg [3:0] addr_a,addr_b;
  reg [7:0] wdata_a,wdata_b;
  
  wire [7:0] rdata_a,rdata_b;
  integer i;
  
  dual_port_RAM DUT (clk,cs,wr_rd_a,wr_rd_b,addr_a,addr_b,wdata_a,wdata_b,rdata_a,rdata_b);
  
  initial begin
    clk=0;
    forever
      #5 clk =~clk;
  end
  
  initial begin $monitor("Time=%3t,clk=%0b,cs=%0b,wr_rd_a=%0b,addr_a=%2d,wdata_a=%3d,rdata_a=%3d,wr_rd_b=%0b,addr_b=%2d,wdata_b=%3d,rdata_b=%3d",$time,clk,cs,wr_rd_a,addr_a,wdata_a,rdata_a,wr_rd_b,addr_b,wdata_b,rdata_b);
    
    cs=1; #10 //chip not selected
    
    wr_rd_a=1;
    for(i=0;i<16;i=i+1)
      repeat(1)@(posedge clk)
        begin
          addr_a=i;
          wdata_a=$random;
        end
    
    wr_rd_b=0;
    for(i=0;i<16;i=i+1)
      repeat(1)@(posedge clk)
        begin
          addr_b=i;
        end
    

  
  cs=0; #10 //chip selected
    
    wr_rd_a=1;            //write at port A
    for(i=0;i<16;i=i+1)
      repeat(1)@(posedge clk)
        begin
          addr_a=i;
          wdata_a=$random;
        end
    
    wr_rd_b=0;             //read at port B
    for(i=0;i<16;i=i+1)
      repeat(1)@(posedge clk)
        begin
          addr_b=i;
        end
    
  #10
    
    wr_rd_b=1;              //write at port B
    for(i=0;i<16;i=i+1)
      repeat(1)@(posedge clk)
        begin
          addr_b=i;
          wdata_b=$random;
        end
    
    wr_rd_a=0;              //read at port A
    for(i=0;i<16;i=i+1)
      repeat(1)@(posedge clk)
        begin
          addr_a=i;
        end    
    
    //Write at a port simultaneously
    
    wr_rd_a=0;wr_rd_b=0;
    addr_a=5;
    addr_b=5;
    #10
    wr_rd_a=1;wr_rd_b=1;
    addr_a=5;
    addr_b=5;
    wdata_a = 77;
    wdata_b = 98;
    #10
    wr_rd_a=0;wr_rd_b=0;

  #20 $finish;
  end

  initial begin
    $dumpfile("wave.vcd");
    $dumpvars;
  end
  
endmodule

wave.vcd
$date
	Sat Jul  9 01:38:12 2022
$end

$version
	Synopsys VCS version Q-2020.03-SP1-1
$end

$timescale
	1ns
$end

$comment Csum: 1 ca2b4afb5b07b5c6 $end


$scope module tb $end
$var reg 1 ! clk $end
$var reg 1 " cs $end
$var reg 1 # wr_rd_a $end
$var reg 1 $ wr_rd_b $end
$var reg 4 % addr_a [3:0] $end
$var reg 4 & addr_b [3:0] $end
$var reg 8 ' wdata_a [7:0] $end
$var reg 8 ( wdata_b [7:0] $end
$var wire 8 ) rdata_a [7:0] $end
$var wire 8 * rdata_b [7:0] $end
$var integer 32 + i $end

$scope module DUT $end
$var wire 1 ! CLK $end
$var wire 1 " CS $end
$var wire 1 # WR_RD_A $end
$var wire 1 $ WR_RD_B $end
$var wire 4 % ADDR_A [3:0] $end
$var wire 4 & ADDR_B [3:0] $end
$var wire 8 ' WDATA_A [7:0] $end
$var wire 8 ( WDATA_B [7:0] $end
$var reg 8 ) RDATA_A [7:0] $end
$var reg 8 * RDATA_B [7:0] $end
$var integer 32 , i $end
$upscope $end

$upscope $end

$enddefinitions $end

#0
$dumpvars
0!
1"
x#
x$
bxxxxxxxx )
bxxxxxxxx *
bxxxx %
bxxxx &
bxxxxxxxxxxxxxxxxxxxxxxxxxxxxxxxx +
bxxxxxxxx '
bxxxxxxxx (
bxxxxxxxxxxxxxxxxxxxxxxxxxxxxxxxx ,
$end
#5
1!
#10
1#
b00000000000000000000000000000000 +
0!
#15
1!
b0000 %
b00100100 '
b00000000000000000000000000000001 +
#20
0!
#25
1!
b0001 %
b10000001 '
b00000000000000000000000000000010 +
#30
0!
#35
1!
b0010 %
b00001001 '
b00000000000000000000000000000011 +
#40
0!
#45
1!
b0011 %
b01100011 '
b00000000000000000000000000000100 +
#50
0!
#55
1!
b0100 %
b00001101 '
b00000000000000000000000000000101 +
#60
0!
#65
1!
b0101 %
b10001101 '
b00000000000000000000000000000110 +
#70
0!
#75
1!
b0110 %
b01100101 '
b00000000000000000000000000000111 +
#80
0!
#85
1!
b0111 %
b00010010 '
b00000000000000000000000000001000 +
#90
0!
#95
1!
b1000 %
b00000001 '
b00000000000000000000000000001001 +
#100
0!
#105
1!
b1001 %
b00001101 '
b00000000000000000000000000001010 +
#110
0!
#115
1!
b1010 %
b01110110 '
b00000000000000000000000000001011 +
#120
0!
#125
1!
b1011 %
b00111101 '
b00000000000000000000000000001100 +
#130
0!
#135
1!
b1100 %
b11101101 '
b00000000000000000000000000001101 +
#140
0!
#145
1!
b1101 %
b10001100 '
b00000000000000000000000000001110 +
#150
0!
#155
1!
b1110 %
b11111001 '
b00000000000000000000000000001111 +
#160
0!
#165
1!
b1111 %
b11000110 '
b00000000000000000000000000010000 +
0$
b00000000000000000000000000000000 +
#170
0!
#175
1!
b0000 &
b00000000000000000000000000000001 +
#180
0!
#185
1!
b0001 &
b00000000000000000000000000000010 +
#190
0!
#195
1!
b0010 &
b00000000000000000000000000000011 +
#200
0!
#205
1!
b0011 &
b00000000000000000000000000000100 +
#210
0!
#215
1!
b0100 &
b00000000000000000000000000000101 +
#220
0!
#225
1!
b0101 &
b00000000000000000000000000000110 +
#230
0!
#235
1!
b0110 &
b00000000000000000000000000000111 +
#240
0!
#245
1!
b0111 &
b00000000000000000000000000001000 +
#250
0!
#255
1!
b1000 &
b00000000000000000000000000001001 +
#260
0!
#265
1!
b1001 &
b00000000000000000000000000001010 +
#270
0!
#275
1!
b1010 &
b00000000000000000000000000001011 +
#280
0!
#285
1!
b1011 &
b00000000000000000000000000001100 +
#290
0!
#295
1!
b1100 &
b00000000000000000000000000001101 +
#300
0!
#305
1!
b1101 &
b00000000000000000000000000001110 +
#310
0!
#315
1!
b1110 &
b00000000000000000000000000001111 +
#320
0!
#325
1!
b1111 &
b00000000000000000000000000010000 +
0"
#330
0!
#335
b00000000000000000000000000000000 +
1!
b0000 %
b11000101 '
b00000000000000000000000000000001 +
b11000110 *
#340
0!
#345
1!
b0001 %
b10101010 '
b00000000000000000000000000000010 +
#350
0!
#355
1!
b0010 %
b11100101 '
b00000000000000000000000000000011 +
#360
0!
#365
1!
b0011 %
b01110111 '
b00000000000000000000000000000100 +
#370
0!
#375
1!
b0100 %
b00010010 '
b00000000000000000000000000000101 +
#380
0!
#385
1!
b0101 %
b10001111 '
b00000000000000000000000000000110 +
#390
0!
#395
1!
b0110 %
b11110010 '
b00000000000000000000000000000111 +
#400
0!
#405
1!
b0111 %
b11001110 '
b00000000000000000000000000001000 +
#410
0!
#415
1!
b1000 %
b11101000 '
b00000000000000000000000000001001 +
#420
0!
#425
1!
b1001 %
b11000101 '
b00000000000000000000000000001010 +
#430
0!
#435
1!
b1010 %
b01011100 '
b00000000000000000000000000001011 +
#440
0!
#445
1!
b1011 %
b10111101 '
b00000000000000000000000000001100 +
#450
0!
#455
1!
b1100 %
b00101101 '
b00000000000000000000000000001101 +
#460
0!
#465
1!
b1101 %
b01100101 '
b00000000000000000000000000001110 +
#470
0!
#475
1!
b1110 %
b01100011 '
b00000000000000000000000000001111 +
#480
0!
#485
1!
b1111 %
b00001010 '
b00000000000000000000000000010000 +
b00000000000000000000000000000000 +
#490
0!
#495
1!
b0000 &
b00000000000000000000000000000001 +
b11000101 *
#500
0!
#505
1!
b0001 &
b00000000000000000000000000000010 +
b10101010 *
#510
0!
#515
1!
b0010 &
b00000000000000000000000000000011 +
b11100101 *
#520
0!
#525
1!
b0011 &
b00000000000000000000000000000100 +
b01110111 *
#530
0!
#535
1!
b0100 &
b00000000000000000000000000000101 +
b00010010 *
#540
0!
#545
1!
b0101 &
b00000000000000000000000000000110 +
b10001111 *
#550
0!
#555
1!
b0110 &
b00000000000000000000000000000111 +
b11110010 *
#560
0!
#565
1!
b0111 &
b00000000000000000000000000001000 +
b11001110 *
#570
0!
#575
1!
b1000 &
b00000000000000000000000000001001 +
b11101000 *
#580
0!
#585
1!
b1001 &
b00000000000000000000000000001010 +
b11000101 *
#590
0!
#595
1!
b1010 &
b00000000000000000000000000001011 +
b01011100 *
#600
0!
#605
1!
b1011 &
b00000000000000000000000000001100 +
b10111101 *
#610
0!
#615
1!
b1100 &
b00000000000000000000000000001101 +
b00101101 *
#620
0!
#625
1!
b1101 &
b00000000000000000000000000001110 +
b01100101 *
#630
0!
#635
1!
b1110 &
b00000000000000000000000000001111 +
b01100011 *
#640
0!
#645
1!
b1111 &
b00000000000000000000000000010000 +
b00001010 *
#650
0!
#655
1$
b00000000000000000000000000000000 +
1!
b0000 &
b10000000 (
b00000000000000000000000000000001 +
#660
0!
#665
1!
b0001 &
b00100000 (
b00000000000000000000000000000010 +
#670
0!
#675
1!
b0010 &
b10101010 (
b00000000000000000000000000000011 +
#680
0!
#685
1!
b0011 &
b10011101 (
b00000000000000000000000000000100 +
#690
0!
#695
1!
b0100 &
b10010110 (
b00000000000000000000000000000101 +
#700
0!
#705
1!
b0101 &
b00010011 (
b00000000000000000000000000000110 +
#710
0!
#715
1!
b0110 &
b00001101 (
b00000000000000000000000000000111 +
#720
0!
#725
1!
b0111 &
b01010011 (
b00000000000000000000000000001000 +
#730
0!
#735
1!
b1000 &
b01101011 (
b00000000000000000000000000001001 +
#740
0!
#745
1!
b1001 &
b11010101 (
b00000000000000000000000000001010 +
#750
0!
#755
1!
b1010 &
b00000010 (
b00000000000000000000000000001011 +
#760
0!
#765
1!
b1011 &
b10101110 (
b00000000000000000000000000001100 +
#770
0!
#775
1!
b1100 &
b00011101 (
b00000000000000000000000000001101 +
#780
0!
#785
1!
b1101 &
b11001111 (
b00000000000000000000000000001110 +
#790
0!
#795
1!
b1110 &
b00100011 (
b00000000000000000000000000001111 +
#800
0!
#805
1!
b1111 &
b00001010 (
b00000000000000000000000000010000 +
0#
b00000000000000000000000000000000 +
b00001010 )
#810
0!
#815
1!
b0000 %
b00000000000000000000000000000001 +
b10000000 )
#820
0!
#825
1!
b0001 %
b00000000000000000000000000000010 +
b00100000 )
#830
0!
#835
1!
b0010 %
b00000000000000000000000000000011 +
b10101010 )
#840
0!
#845
1!
b0011 %
b00000000000000000000000000000100 +
b10011101 )
#850
0!
#855
1!
b0100 %
b00000000000000000000000000000101 +
b10010110 )
#860
0!
#865
1!
b0101 %
b00000000000000000000000000000110 +
b00010011 )
#870
0!
#875
1!
b0110 %
b00000000000000000000000000000111 +
b00001101 )
#880
0!
#885
1!
b0111 %
b00000000000000000000000000001000 +
b01010011 )
#890
0!
#895
1!
b1000 %
b00000000000000000000000000001001 +
b01101011 )
#900
0!
#905
1!
b1001 %
b00000000000000000000000000001010 +
b11010101 )
#910
0!
#915
1!
b1010 %
b00000000000000000000000000001011 +
b00000010 )
#920
0!
#925
1!
b1011 %
b00000000000000000000000000001100 +
b10101110 )
#930
0!
#935
1!
b1100 %
b00000000000000000000000000001101 +
b00011101 )
#940
0!
#945
1!
b1101 %
b00000000000000000000000000001110 +
b11001111 )
#950
0!
#955
1!
b1110 %
b00000000000000000000000000001111 +
b00100011 )
#960
0!
#965
1!
b1111 %
b00000000000000000000000000010000 +
0$
b0101 %
b0101 &
b00010011 )
b00010011 *
#970
0!
#975
1#
1$
b01001101 '
b01100010 (
1!
#980
0!
#985
0#
0$
1!
b01100010 )
b01100010 *
